heroicons/__init__.py
heroicons/__main__.py
heroicons/cli.py
heroicons/heroicons.zip
heroicons/jinja.py
heroicons/py.typed
heroicons/templatetags/__init__.py
heroicons/templatetags/heroicons.py
heroicons-2.13.0.dist-info/licenses/LICENSE
heroicons-2.13.0.dist-info/METADATA
heroicons-2.13.0.dist-info/WHEEL
heroicons-2.13.0.dist-info/top_level.txt
heroicons-2.13.0.dist-info/RECORD
